README.md
setup.cfg
setup.py
short_stuff/__init__.py
short_stuff/django_test_settings.py
short_stuff/lib.py
short_stuff.egg-info/PKG-INFO
short_stuff.egg-info/SOURCES.txt
short_stuff.egg-info/dependency_links.txt
short_stuff.egg-info/top_level.txt
short_stuff/django/__init__.py
short_stuff/django/converters.py
short_stuff/django/models.py
short_stuff/django/serializers.py
short_stuff/tests/__init__.py
short_stuff/tests/test_lib.py
short_stuff/tests/dummy_app/__init__.py
short_stuff/tests/dummy_app/admin.py
short_stuff/tests/dummy_app/apps.py
short_stuff/tests/dummy_app/models.py
short_stuff/tests/dummy_app/tests.py
short_stuff/tests/dummy_app/views.py
short_stuff/tests/dummy_app/migrations/0001_initial.py
short_stuff/tests/dummy_app/migrations/__init__.py
short_stuff/tests/dummy_app/tests/__init__.py
short_stuff/tests/dummy_app/tests/test_converters.py
short_stuff/tests/dummy_app/tests/test_models.py
short_stuff/tests/dummy_app/tests/test_serializers.py