Metadata-Version: 2.1
Name: short-stuff
Version: 1.0.1
Summary: Set of utilities for managing unique shortcodes.
Home-page: https://github.com/Artconomy/short_stuff
Author: Fox Danger Piacenti
Author-email: fox@artconomy.com
License: UNKNOWN
Download-URL: https://github.com/Artconomy/short_stuff/archive/1.0.1.tar.gz
Platform: UNKNOWN
Classifier: Development Status :: 3 - Alpha
Classifier: Programming Language :: Python :: 3
Classifier: Programming Language :: Python :: 3.6
Classifier: Programming Language :: Python :: 3.7
Classifier: Programming Language :: Python :: 3.8
Classifier: License :: Public Domain
Classifier: Operating System :: OS Independent
